LICENSE
MANIFEST.in
README.md
setup.py
wechatpayv3/__init__.py
wechatpayv3/apply4subject.py
wechatpayv3/applyment.py
wechatpayv3/businesscircle.py
wechatpayv3/capital.py
wechatpayv3/complaint.py
wechatpayv3/core.py
wechatpayv3/fapiao.py
wechatpayv3/goldplan.py
wechatpayv3/marketing.py
wechatpayv3/media.py
wechatpayv3/merchantrisk.py
wechatpayv3/parking.py
wechatpayv3/payscore.py
wechatpayv3/profitsharing.py
wechatpayv3/smartguide.py
wechatpayv3/transaction.py
wechatpayv3/transfer.py
wechatpayv3/type.py
wechatpayv3/utils.py
wechatpayv3_fix.egg-info/PKG-INFO
wechatpayv3_fix.egg-info/SOURCES.txt
wechatpayv3_fix.egg-info/dependency_links.txt
wechatpayv3_fix.egg-info/requires.txt
wechatpayv3_fix.egg-info/top_level.txt