Metadata-Version: 2.1
Name: wechatpayv3-fix
Version: 1.2.38
Summary: [修复版] 微信支付 API v3 Python SDK(python sdk for wechatpay v3)，fork from: https://github.com/minibear2021/wechatpayv3
Home-page: https://github.com/houxiaohou/wechatpayv3
Author: houxiaohou
License: MIT
Keywords: python sdk wechatpay api v3 微信支付
Classifier: Development Status :: 5 - Production/Stable
Classifier: Topic :: Office/Business :: Financial
Classifier: License :: OSI Approved :: MIT License
Classifier: Programming Language :: Python :: 3
License-File: LICENSE
